LICENSE
MANIFEST.in
README.md
requirements.txt
setup.py
test-requirements.txt
conf/__init__.py
conf/config.py
conf/configrh.py
contrib/freshmaker-cli
contrib/freshmaker.wsgi
fedmsg.d/freshmaker-logging.py
fedmsg.d/freshmaker-rh.py.disabled
fedmsg.d/freshmaker-scheduler.py
fedmsg.d/freshmaker.py
freshmaker/__init__.py
freshmaker/api_utils.py
freshmaker/auth.py
freshmaker/config.py
freshmaker/consumer.py
freshmaker/errata.py
freshmaker/errors.py
freshmaker/events.py
freshmaker/kojiservice.py
freshmaker/lightblue.py
freshmaker/logger.py
freshmaker/manage.py
freshmaker/mbs.py
freshmaker/messaging.py
freshmaker/models.py
freshmaker/odcsclient.py
freshmaker/pdc.py
freshmaker/proxy.py
freshmaker/pulp.py
freshmaker/security_data.py
freshmaker/types.py
freshmaker/utils.py
freshmaker/views.py
freshmaker.egg-info/PKG-INFO
freshmaker.egg-info/SOURCES.txt
freshmaker.egg-info/dependency_links.txt
freshmaker.egg-info/entry_points.txt
freshmaker.egg-info/not-zip-safe
freshmaker.egg-info/requires.txt
freshmaker.egg-info/top_level.txt
freshmaker/handlers/__init__.py
freshmaker/handlers/bodhi/__init__.py
freshmaker/handlers/bodhi/update_complete_stable.py
freshmaker/handlers/brew/__init__.py
freshmaker/handlers/brew/container_task_state_change.py
freshmaker/handlers/brew/sign_rpm.py
freshmaker/handlers/errata/__init__.py
freshmaker/handlers/errata/errata_advisory_rpms_signed.py
freshmaker/handlers/errata/errata_advisory_state_changed.py
freshmaker/handlers/git/__init__.py
freshmaker/handlers/git/dockerfile_change.py
freshmaker/handlers/git/module_metadata_change.py
freshmaker/handlers/git/rpm_spec_change.py
freshmaker/handlers/internal/__init__.py
freshmaker/handlers/internal/manual_rebuild.py
freshmaker/handlers/koji/__init__.py
freshmaker/handlers/koji/task_state_change.py
freshmaker/handlers/mbs/__init__.py
freshmaker/handlers/mbs/module_state_change.py
freshmaker/handlers/odcs/__init__.py
freshmaker/handlers/odcs/compose_state_change.py
freshmaker/migrations/README
freshmaker/migrations/alembic.ini
freshmaker/migrations/env.py
freshmaker/migrations/script.py.mako
freshmaker/migrations/versions/2acc88805404_add_user_model.py
freshmaker/migrations/versions/2f5a2f4385a0_add_manual_triggered_to_event_model.py
