Metadata-Version: 1.1
Name: freshmaker
Version: 0.1.0
Summary: Continuous Compose Service
Home-page: https://pagure.io/freshmaker/
Author: The Factory 2.0 Team
Author-email: freshmaker-owner@fedoraproject.org
License: MIT
Keywords: freshmaker continuous compose service modularity fedora
Platform: UNKNOWN
Classifier: Programming Language :: Python
Classifier: Topic :: Software Development :: Build Tools
